{
    "title": "Global Button Styles (button)",
    "tag": "ilw-global-button-button",
    "github": "https://github.com/web-illinois/toolkit-management/",
    "type": "stylesheet",
    "element-name": "button",
    "description": "The Global WIGG Stylesheet contains styles for a single button. This is using the 'button' element.",
    "builder-version": "latest",
    "version": "3.7.1-beta",
    "date": "11/14/2025",
    "css": "",
    "js": "",
    "production": false,
    "notes": "",
    "parent-style": "text-align: center;",
    "samples": [
        {
            "name": "default",
            "description": "Single button",
            "text": "Link 1"
        }
    ],
    "attributes-fixed": [],
    "attributes-text": [],
    "attributes": [],
    "classes-fixed": [
        {
            "name": "ilw-button",
            "description": "Button group class",
            "depreciated": false,
            "value": "ilw-button"
        }
    ],
    "classes": [
        {
            "name": "theme",
            "description": "Color theme used",
            "depreciated": false,
            "values": [
                "",
                "ilw-theme-blue-outline",
                "ilw-theme-orange-outline",
                "ilw-theme-blue-solid",
                "ilw-theme-orange-solid",
                "ilw-theme-blue-inverse",
                "ilw-theme-orange-inverse"
            ]
        },
        {
            "name": "width",
            "description": "Width of buttons",
            "depreciated": false,
            "values": [
                "",
                "ilw-width-full"
            ]
        },
        {
            "name": "size",
            "description": "Size of buttons",
            "depreciated": false,
            "values": [
                "",
                "ilw-size-large"
            ]
        }
    ],
    "css-variables": []
}
